LICENSE.rst
MANIFEST.in
README.rst
setup.py
src/node/__init__.py
src/node.ext.xmi.egg-info/PKG-INFO
src/node.ext.xmi.egg-info/SOURCES.txt
src/node.ext.xmi.egg-info/dependency_links.txt
src/node.ext.xmi.egg-info/entry_points.txt
src/node.ext.xmi.egg-info/namespace_packages.txt
src/node.ext.xmi.egg-info/not-zip-safe
src/node.ext.xmi.egg-info/requires.txt
src/node.ext.xmi.egg-info/top_level.txt
src/node/ext/__init__.py
src/node/ext/xmi/__init__.py
src/node/ext/xmi/_api.py
src/node/ext/xmi/_api.rst
src/node/ext/xmi/configure.zcml
src/node/ext/xmi/interfaces.py
src/node/ext/xmi/tests.py
src/node/ext/xmi/testing/__init__.py
src/node/ext/xmi/testing/data/examplegg.uml
src/node/ext/xmi/testing/data/pyegg.profile.uml